Metadata-Version: 1.0
Name: mysql-tools
Version: 0.0.1
Summary: mysql_tools
Home-page: https://github.com/Shimon-Cheung
Author: xmzhang
Author-email: 25337942@qq.com
License: UNKNOWN
Platform: UNKNOWN
